{
  "articles": [
    {
      "date": "2026-04-24",
      "segment": "war",
      "filename": "2026-04-24-war.html",
      "headline": "Trump's Firing Spree and the Kharg Island Backlash: A New Era of US Military Recklessness",
      "category": "GEOPOLITICAL ANALYSIS",
      "color": "#ef4444",
      "published_at": "April 24, 2026"
    },
    {
      "date": "2026-04-24",
      "segment": "epstein",
      "filename": "2026-04-24-epstein.html",
      "headline": "Lutnick's Evasive Silence on Epstein: A Wall of Omerta Around Wall Street's Elite",
      "category": "INVESTIGATION",
      "color": "#d4a855",
      "published_at": "April 24, 2026"
    },
    {
      "date": "2026-04-23",
      "segment": "war",
      "filename": "2026-04-23-war.html",
      "headline": "IRGC's Underwater Gambit: Hormuz Cables Targeted, India's Digital Lifeline at Risk",
      "category": "GEOPOLITICAL ANALYSIS",
      "color": "#ef4444",
      "published_at": "April 23, 2026"
    },
    {
      "date": "2026-04-23",
      "segment": "epstein",
      "filename": "2026-04-23-epstein.html",
      "headline": "Trump's Desperate Bid to Silence Epstein Truth: DOJ Runs from Testimony as Release Halted",
      "category": "INVESTIGATION",
      "color": "#d4a855",
      "published_at": "April 23, 2026"
    },
    {
      "date": "2026-04-22",
      "segment": "war",
      "filename": "2026-04-22-war.html",
      "headline": "Trump's Hormuz Bluff Called: Iran's Diplomatic Power Play Exposes DC Divisions",
      "category": "GEOPOLITICAL ANALYSIS",
      "color": "#ef4444",
      "published_at": "April 22, 2026"
    },
    {
      "date": "2026-04-22",
      "segment": "epstein",
      "filename": "2026-04-22-epstein.html",
      "headline": "Trump DOJ 'Shredding Docs' and Bannon's Files Resurface: The Epstein Cover-up's Deliberate Destruction",
      "category": "INVESTIGATION",
      "color": "#d4a855",
      "published_at": "April 22, 2026"
    },
    {
      "date": "2026-04-21",
      "segment": "war",
      "filename": "2026-04-21-war.html",
      "headline": "Jeffries' Blunt Question: Why is Hegseth Still Around as Trump's Seizures Escalate?",
      "category": "GEOPOLITICAL ANALYSIS",
      "color": "#ef4444",
      "published_at": "April 21, 2026"
    },
    {
      "date": "2026-04-21",
      "segment": "epstein",
      "filename": "2026-04-21-epstein.html",
      "headline": "Kash Patel's Bombshell Threat: The Epstein Cover-up Escalates Towards Imminent Arrests",
      "category": "INVESTIGATION",
      "color": "#d4a855",
      "published_at": "April 21, 2026"
    },
    {
      "date": "2026-04-20",
      "segment": "war",
      "filename": "2026-04-20-war.html",
      "headline": "Kharg Island's Bloody Nose: Iran's Missile Response Shatters US Dominance, Indian Markets Brace",
      "category": "GEOPOLITICAL ANALYSIS",
      "color": "#ef4444",
      "published_at": "April 20, 2026"
    },
    {
      "date": "2026-04-20",
      "segment": "epstein",
      "filename": "2026-04-20-epstein.html",
      "headline": "Melania Trump's Unscripted Move: The Epstein Files and the Unraveling Cover-up",
      "category": "INVESTIGATION",
      "color": "#d4a855",
      "published_at": "April 20, 2026"
    },
    {
      "date": "2026-04-19",
      "segment": "war",
      "filename": "2026-04-19-war.html",
      "headline": "Pope Leo XIV's Angolan Gambit: A Diplomatic Smoke Screen as Iran's Strait Grip Tightens",
      "category": "GEOPOLITICAL ANALYSIS",
      "color": "#ef4444",
      "published_at": "April 19, 2026"
    },
    {
      "date": "2026-04-19",
      "segment": "epstein",
      "filename": "2026-04-19-epstein.html",
      "headline": "Trump's Shredded Files and Bannon's Shadow: The Epstein Cover-up's New Frontier",
      "category": "INVESTIGATION",
      "color": "#d4a855",
      "published_at": "April 19, 2026"
    },
    {
      "date": "2026-04-18",
      "segment": "epstein",
      "filename": "2026-04-18-epstein.html",
      "headline": "DOJ's Epstein Silence: Wexner's 'S*x Services' Bombshell, Trump's Judicial Gambit, and India's Eroding Trust",
      "category": "INVESTIGATION",
      "color": "#d4a855",
      "published_at": "April 18, 2026"
    },
    {
      "date": "2026-04-17",
      "segment": "war",
      "filename": "2026-04-17-war.html",
      "headline": "Hormuz Endgame: America's Resource Grab Accelerates, Indian Defence Stocks Signal The Play",
      "category": "GEOPOLITICAL ANALYSIS",
      "color": "#ef4444",
      "published_at": "April 17, 2026"
    },
    {
      "date": "2026-04-17",
      "segment": "epstein",
      "filename": "2026-04-17-epstein.html",
      "headline": "DOJ's Epstein Cover-Up: Trump's Teleportation Delusions and the Silent Billionaire Cartel's Grip on India",
      "category": "INVESTIGATION",
      "color": "#d4a855",
      "published_at": "April 17, 2026"
    },
    {
      "date": "2026-04-16",
      "segment": "war",
      "filename": "2026-04-16-war.html",
      "headline": "Hormuz Endgame: America's Oil Grab and India's Defence Dividend",
      "category": "GEOPOLITICAL ANALYSIS",
      "color": "#ef4444",
      "published_at": "April 16, 2026"
    },
    {
      "date": "2026-04-16",
      "segment": "epstein",
      "filename": "2026-04-16-epstein.html",
      "headline": "DOJ's Epstein Obstruction: Trump's Hoax Claims and the Silent Billionaire Cartel Undermining India",
      "category": "INVESTIGATION",
      "color": "#d4a855",
      "published_at": "April 16, 2026"
    }
  ]
}