{
  "updated_at": "2026-04-24T14:04:03.165184+05:30",
  "total_closed": 38,
  "win_rate_pct": 57.9,
  "avg_pnl_pct": 1.92,
  "recent": [
    {
      "signal_id": "BRK-2026-04-23-TECHM",
      "spread_name": "Strategy 641",
      "category": "phase_c",
      "tier": "SIGNAL",
      "event_headline": "Phase C break on TECHM: z=-4.6, expected=-0.19, actual=-3.14",
      "open_date": "2026-04-23",
      "close_date": "2026-04-24",
      "days_open": 1,
      "peak_pnl_pct": 4.8,
      "final_pnl_pct": 4.8,
      "close_reason": "STOPPED_OUT_ZCROSS"
    },
    {
      "signal_id": "BRK-2026-04-23-CROMPTON",
      "spread_name": "Strategy 849",
      "category": "phase_c",
      "tier": "SIGNAL",
      "event_headline": "Phase C break on CROMPTON: z=-2.74, expected=-0.28, actual=-2.48",
      "open_date": "2026-04-23",
      "close_date": "2026-04-24",
      "days_open": 1,
      "peak_pnl_pct": 3.79,
      "final_pnl_pct": 2.93,
      "close_reason": "STOPPED_OUT_ZCROSS"
    },
    {
      "signal_id": "BRK-2026-04-23-TMPV",
      "spread_name": "Strategy 645",
      "category": "phase_c",
      "tier": "SIGNAL",
      "event_headline": "Phase C break on TMPV: z=2.17, expected=-1.55, actual=0.08",
      "open_date": "2026-04-23",
      "close_date": "2026-04-24",
      "days_open": 1,
      "peak_pnl_pct": 2.28,
      "final_pnl_pct": 2.28,
      "close_reason": "STOPPED_OUT_ZCROSS"
    },
    {
      "signal_id": "BRK-2026-04-23-RECLTD",
      "spread_name": "Strategy 281",
      "category": "phase_c",
      "tier": "SIGNAL",
      "event_headline": "Phase C break on RECLTD: z=1.84, expected=-1.41, actual=-0.05",
      "open_date": "2026-04-23",
      "close_date": "2026-04-24",
      "days_open": 1,
      "peak_pnl_pct": 1.99,
      "final_pnl_pct": 1.99,
      "close_reason": "STOPPED_OUT_ZCROSS"
    },
    {
      "signal_id": "BRK-2026-04-23-PETRONET",
      "spread_name": "Strategy 156",
      "category": "phase_c",
      "tier": "SIGNAL",
      "event_headline": "Phase C break on PETRONET: z=1.83, expected=-1.56, actual=0.45",
      "open_date": "2026-04-23",
      "close_date": "2026-04-24",
      "days_open": 1,
      "peak_pnl_pct": 1.28,
      "final_pnl_pct": 1.28,
      "close_reason": "STOPPED_OUT_ZCROSS"
    },
    {
      "signal_id": "BRK-2026-04-23-HDFCAMC",
      "spread_name": "Strategy 582",
      "category": "phase_c",
      "tier": "SIGNAL",
      "event_headline": "Phase C break on HDFCAMC: z=1.53, expected=-1.55, actual=-0.01",
      "open_date": "2026-04-23",
      "close_date": "2026-04-24",
      "days_open": 0,
      "peak_pnl_pct": 1.49,
      "final_pnl_pct": 0.66,
      "close_reason": "STOPPED_OUT_ZCROSS"
    },
    {
      "signal_id": "BRK-2026-04-23-MOTILALOFS",
      "spread_name": "Strategy 578",
      "category": "phase_c",
      "tier": "SIGNAL",
      "event_headline": "Phase C break on MOTILALOFS: z=1.57, expected=-2.45, actual=0.01",
      "open_date": "2026-04-23",
      "close_date": "2026-04-24",
      "days_open": 0,
      "peak_pnl_pct": 2.97,
      "final_pnl_pct": 2.97,
      "close_reason": "STOPPED_OUT_ZCROSS"
    },
    {
      "signal_id": "BRK-2026-04-23-EXIDEIND",
      "spread_name": "Strategy 305",
      "category": "phase_c",
      "tier": "SIGNAL",
      "event_headline": "Phase C break on EXIDEIND: z=2.23, expected=-1.91, actual=-0.3",
      "open_date": "2026-04-23",
      "close_date": "2026-04-24",
      "days_open": 0,
      "peak_pnl_pct": 3.17,
      "final_pnl_pct": 3.17,
      "close_reason": "STOPPED_OUT_ZCROSS"
    },
    {
      "signal_id": "BRK-2026-04-23-VEDL",
      "spread_name": "Strategy 971",
      "category": "phase_c",
      "tier": "SIGNAL",
      "event_headline": "Phase C break on VEDL: z=-1.65, expected=-1.26, actual=-3.3",
      "open_date": "2026-04-23",
      "close_date": "2026-04-24",
      "days_open": 0,
      "peak_pnl_pct": 4.59,
      "final_pnl_pct": 4.59,
      "close_reason": "STOPPED_OUT_ZCROSS"
    },
    {
      "signal_id": "BRK-2026-04-23-HAVELLS",
      "spread_name": "Strategy 409",
      "category": "phase_c",
      "tier": "SIGNAL",
      "event_headline": "Phase C break on HAVELLS: z=-1.55, expected=-0.68, actual=-2.5",
      "open_date": "2026-04-23",
      "close_date": "2026-04-24",
      "days_open": 0,
      "peak_pnl_pct": 3.67,
      "final_pnl_pct": 3.67,
      "close_reason": "STOPPED_OUT_ZCROSS"
    },
    {
      "signal_id": "BRK-2026-04-23-TVSMOTOR",
      "spread_name": "Strategy 638",
      "category": "phase_c",
      "tier": "SIGNAL",
      "event_headline": "Phase C break on TVSMOTOR: z=-1.51, expected=-0.18, actual=-3.77",
      "open_date": "2026-04-23",
      "close_date": "2026-04-24",
      "days_open": 0,
      "peak_pnl_pct": 4.47,
      "final_pnl_pct": 4.47,
      "close_reason": "STOPPED_OUT_ZCROSS"
    },
    {
      "signal_id": "BRK-2026-04-23-APLAPOLLO",
      "spread_name": "Strategy 349",
      "category": "phase_c",
      "tier": "SIGNAL",
      "event_headline": "Phase C break on APLAPOLLO: z=-1.89, expected=-0.8, actual=-3.41",
      "open_date": "2026-04-23",
      "close_date": "2026-04-24",
      "days_open": 0,
      "peak_pnl_pct": 5.22,
      "final_pnl_pct": 5.22,
      "close_reason": "STOPPED_OUT_ZCROSS"
    },
    {
      "signal_id": "BRK-2026-04-23-MPHASIS",
      "spread_name": "Strategy 548",
      "category": "phase_c",
      "tier": "SIGNAL",
      "event_headline": "Phase C break on MPHASIS: z=-1.59, expected=-0.6, actual=-1.95",
      "open_date": "2026-04-23",
      "close_date": "2026-04-24",
      "days_open": 0,
      "peak_pnl_pct": 4.55,
      "final_pnl_pct": 4.55,
      "close_reason": "STOPPED_OUT_ZCROSS"
    },
    {
      "signal_id": "BRK-2026-04-23-BLUESTARCO",
      "spread_name": "Strategy 216",
      "category": "phase_c",
      "tier": "SIGNAL",
      "event_headline": "Phase C break on BLUESTARCO: z=-1.56, expected=-1.04, actual=-2.76",
      "open_date": "2026-04-23",
      "close_date": "2026-04-24",
      "days_open": 0,
      "peak_pnl_pct": 4.23,
      "final_pnl_pct": 4.23,
      "close_reason": "STOPPED_OUT_ZCROSS"
    },
    {
      "signal_id": "BRK-2026-04-23-UNIONBANK",
      "spread_name": "Strategy 447",
      "category": "phase_c",
      "tier": "SIGNAL",
      "event_headline": "Phase C break on UNIONBANK: z=-2.06, expected=-1.42, actual=-6.39",
      "open_date": "2026-04-23",
      "close_date": "2026-04-24",
      "days_open": 0,
      "peak_pnl_pct": 9.36,
      "final_pnl_pct": 9.36,
      "close_reason": "STOPPED_OUT_ZCROSS"
    },
    {
      "signal_id": "BRK-2026-04-23-SONACOMS",
      "spread_name": "Strategy 801",
      "category": "phase_c",
      "tier": "SIGNAL",
      "event_headline": "Phase C break on SONACOMS: z=-1.82, expected=-1.05, actual=-2.84",
      "open_date": "2026-04-23",
      "close_date": "2026-04-24",
      "days_open": 0,
      "peak_pnl_pct": 3.79,
      "final_pnl_pct": 3.79,
      "close_reason": "STOPPED_OUT_ZCROSS"
    },
    {
      "signal_id": "BRK-2026-04-23-TATATECH",
      "spread_name": "Strategy 656",
      "category": "phase_c",
      "tier": "SIGNAL",
      "event_headline": "Phase C break on TATATECH: z=-1.67, expected=-0.91, actual=-2.15",
      "open_date": "2026-04-23",
      "close_date": "2026-04-24",
      "days_open": 0,
      "peak_pnl_pct": 3.31,
      "final_pnl_pct": 3.31,
      "close_reason": "STOPPED_OUT_ZCROSS"
    },
    {
      "signal_id": "BRK-2026-04-24-NMDC",
      "spread_name": "Strategy 371",
      "category": "phase_c",
      "tier": "EXPLORING",
      "event_headline": "Phase C break on NMDC: z=1.57, expected=-1.48, actual=0.13",
      "open_date": "2026-04-24",
      "close_date": "2026-04-24",
      "days_open": 0,
      "peak_pnl_pct": 0,
      "final_pnl_pct": -1.71,
      "close_reason": "STOPPED_OUT_ZCROSS"
    },
    {
      "signal_id": "BRK-2026-04-24-IEX",
      "spread_name": "Strategy 824",
      "category": "phase_c",
      "tier": "EXPLORING",
      "event_headline": "Phase C break on IEX: z=1.61, expected=-2.07, actual=-0.76",
      "open_date": "2026-04-24",
      "close_date": "2026-04-24",
      "days_open": 0,
      "peak_pnl_pct": 4.05,
      "final_pnl_pct": 4.05,
      "close_reason": "STOPPED_OUT_ZCROSS"
    },
    {
      "signal_id": "BRK-2026-04-23-PFC",
      "spread_name": "Strategy 264",
      "category": "phase_c",
      "tier": "SIGNAL",
      "event_headline": "Phase C break on PFC: z=1.66, expected=-1.36, actual=0.29",
      "open_date": "2026-04-23",
      "close_date": "2026-04-23",
      "days_open": 0,
      "peak_pnl_pct": 0,
      "final_pnl_pct": -0.66,
      "close_reason": "STOPPED_OUT_ZCROSS"
    }
  ]
}